rsocks/__init__.py
rsocks/cli.py
rsocks/green.py
rsocks/pool.py
rsocks/server.py
rsocks/utils.py
rsocks-0.4.0.dist-info/LICENSE
rsocks-0.4.0.dist-info/METADATA
rsocks-0.4.0.dist-info/WHEEL
rsocks-0.4.0.dist-info/entry_points.txt
rsocks-0.4.0.dist-info/top_level.txt
rsocks-0.4.0.dist-info/RECORD
