Metadata-Version: 2.1
Name: rsocks
Version: 0.4.0
Summary: A SOCKS reverse proxy server.
Home-page: https://github.com/tonyseek/rsocks
Author: Jiangge Zhang
Author-email: tonyseek@gmail.com
License: MIT
Platform: Any
Classifier: Development Status :: 3 - Alpha
Classifier: License :: OSI Approved :: MIT License
Classifier: Operating System :: OS Independent
Classifier: Programming Language :: Python
Classifier: Programming Language :: Python :: 2.7
Classifier: Programming Language :: Python :: 3.3
Classifier: Programming Language :: Python :: 3.4
Classifier: Programming Language :: Python :: 3.10
Classifier: Programming Language :: Python :: Implementation :: PyPy
License-File: LICENSE
Requires-Dist: PySocks (<1.8,>=1.7.1)
Requires-Dist: eventlet (<0.34,>=0.31)
Requires-Dist: click (<3.4,>=3.3)
Requires-Dist: toml.py (<0.2,>=0.1)
Requires-Dist: six
